rapidstats/__init__.py
rapidstats/_bootstrap.py
rapidstats/_corr.py
rapidstats/_distributions.py
rapidstats/_general.py
rapidstats/_polars/__init__.py
rapidstats/_polars/_format.py
rapidstats/_polars/_numeric.py
rapidstats/_polars/_utils.py
rapidstats/_rustystats.pyi
rapidstats/_rustystats.pypy39-pp73-ppc_64-linux-gnu.so
rapidstats/_utils.py
rapidstats/bin.py
rapidstats/drift.py
rapidstats/metrics.py
rapidstats/polars.py
rapidstats/preprocessing.py
rapidstats/py.typed
rapidstats/selection.py
rapidstats/viz.py
rapidstats-0.4.0.dist-info/METADATA
rapidstats-0.4.0.dist-info/WHEEL
rapidstats-0.4.0.dist-info/licenses/LICENSE
rapidstats-0.4.0.dist-info/RECORD
