Metadata-Version: 2.4
Name: rapidstats
Version: 0.4.0
Classifier: Programming Language :: Python :: 3
Classifier: License :: OSI Approved :: MIT License
Requires-Dist: polars>=1.0.0,!=1.26.0
Requires-Dist: narwhals>=1.0.0
Requires-Dist: tqdm
Requires-Dist: pyarrow>=7.0.0 ; extra == 'pyarrow'
Provides-Extra: pyarrow
License-File: LICENSE
Summary: A library that implements fast statistical routines
Author-email: Cangyuan Li <everest229@gmail.com>
Requires-Python: >=3.9
Project-URL: Bug Reports, https://github.com/CangyuanLi/rapidstats/issues
Project-URL: Homepage, https://github.com/CangyuanLi/rapidstats
Project-URL: Source, https://github.com/CangyuanLi/rapidstats
